{"composite_breakdown_label":"","computation_units":"\uc810","copyright":"","data_footnote":"","data_non_statistical":false,"data_notice_class":"","data_notice_heading":"","data_notice_text":"","data_show_map":false,"data_start_values":[{"field":"\uc9c0\uc5ed","value":"\ud55c\uad6d"}],"embedded_feature_footer":"","embedded_feature_html":"","embedded_feature_tab_title":"","embedded_feature_title":"","embedded_feature_url":"","expected_disaggregations":[],"graph_annotations":[],"graph_limits":[],"graph_stacked_disaggregation":"","graph_title":"\uc815\ubd80\uc758 \ubcc0\ud654 \ub300\uc751\ub825","graph_titles":[],"graph_type":"bar","indicator_name":"\uc815\ubd80\uc758 \ubcc0\ud654 \ub300\uc751\ub825","indicator_number":"2.1.3","national_geographical_coverage":"","page_content":"","permalink":"","precision":[],"reporting_status":"complete","sort":"","standalone":false,"tags":[],"computation_definitions":"\uc601   \uc5ed: \uc5ed\ub7c9<br> \ud558\uc704\uc601\uc5ed: \uc81c\ub3c4\uc801 \uc5ed\ub7c9","SDG_INDICATOR":"\uc815\ubd80\uc758 \ubcc0\ud654 \ub300\uc751\ub825: Government' responsivensess to change","indicator_definition":"\uae30\uc5c5\uacbd\uc601\uc790\ub4e4\uc5d0\uac8c \uc815\ubd80\uc758 \ubcc0\ud654\uc5d0 \ub300\ud55c \ub300\uc751\ub825\uc758 \ud3c9\uac00\ub97c 1~7\uc810 \ucc99\ub3c4\ub85c \uc751\ub2f5\ud558\uac8c \ud55c \uacb0\uacfc\ub97c 100\uc810\uc73c\ub85c \ud658\uc0b0","indicator_importance":"\ube60\ub978 \ud658\uacbd\ubcc0\ud654 \uc18d\ub3c4\uc5d0 \uc815\ubd80\uac00 \uc801\uadf9\uc801\uc73c\ub85c \ub300\uc751\ud560 \uc218 \uc788\ub294 \uc815\ub3c4\ub294 \uad11\uc5ed \uc218\uc900\uc5d0\uc11c \uacbd\uc7c1\ud558\ub294 \uacbd\uc81c\uc8fc\uccb4 \ub4e4\uc5d0\uac8c \ub9e4\uc6b0 \uc911\uc694\ud55c \uc81c\ub3c4\uc801 \uc5ed\ub7c9\uc774 \ub428","computation_calculations":"\uae30\uc5c5\uacbd\uc601\uc790\ub4e4\uc5d0\uac8c \uc815\ubd80\uc758 \ubcc0\ud654\uc5d0 \ub300\ud55c \ub300\uc751\ub825\uc758 \ud3c9\uac00\ub97c 1~7\uc810 \ucc99\ub3c4\ub85c \uc751\ub2f5\ud558\uac8c \ud55c \uacb0\uacfc\ub97c 100\uc810\uc73c\ub85c \ud658\uc0b0","statistics_name":"World Economic Forum > Global Competitiveness Index, 2019","computation_coverage":"2019\ub144","data_download":"","national_metadata_updated_date":"2022-09-16","national_data_updated_date":"2022-09-13","national_metadata_update_url_text":"2022-09-16: see changes on GitHub","national_metadata_update_url":"https://github.com/kostat-gi/data/commit/076e05da53993558f746c1757162397a85a72855","national_data_update_url_text":"2022-09-13: see changes on GitHub","national_data_update_url":"https://github.com/kostat-gi/data/commit/0437e7c6014f1438c874f7b0ada2f6273c2b81c4","indicator":"2.1.3","target_id":"2.1","sdg_goal":"2","indicator_sort_order":"02-01-03"}